gadfasthealth/__init__.py
gadfasthealth-0.0.1.dist-info/LICENSE
gadfasthealth-0.0.1.dist-info/METADATA
gadfasthealth-0.0.1.dist-info/WHEEL
gadfasthealth-0.0.1.dist-info/top_level.txt
gadfasthealth-0.0.1.dist-info/RECORD
