Metadata-Version: 2.1
Name: gadfasthealth
Version: 0.0.1
Summary: FastAPI health check extension for Kubernetes liveness, readiness, and startup probes.
Home-page: https://github.com/AlexDemure/gadfasthealth
Author: Alexander Grishchenko
Author-email: alexanderdemure@gmail.com
Classifier: Programming Language :: Python :: 3
Classifier: License :: OSI Approved :: MIT License
Classifier: Operating System :: OS Independent
Requires-Python: >=3.8
License-File: LICENSE
Requires-Dist: fastapi
